django_batteries/__init__.py
django_batteries-25.0.dist-info/LICENSE
django_batteries-25.0.dist-info/WHEEL
django_batteries-25.0.dist-info/METADATA
django_batteries-25.0.dist-info/RECORD
