Metadata-Version: 2.1
Name: django-batteries
Version: 25.0
Summary: ================
Author-email: Carlton Gibson <carlton.gibson@noumenal.es>
Classifier: License :: OSI Approved :: MIT License
Project-URL: Home, https://noumenal.es/django-batteries/
